<?xml version="1.0" ?><summary fileFormatVersion="101"><methods><method id="android.content.ClipData newUri(android.content.ContentResolver,java.lang.CharSequence,android.net.Uri)"><flows><flow isAlias="true"><from sourceSinkType="Parameter" ParameterIndex="0" BaseType="android.content.ContentResolver"></from><to sourceSinkType="GapBaseObject" BaseType="android.content.ContentResolver" gap="2"></to></flow><flow isAlias="true"><from sourceSinkType="Parameter" ParameterIndex="2" BaseType="android.net.Uri"></from><to sourceSinkType="GapBaseObject" BaseType="android.net.Uri" gap="1"></to></flow><flow isAlias="true"><from sourceSinkType="Parameter" ParameterIndex="2" BaseType="android.net.Uri"></from><to sourceSinkType="Return" BaseType="android.content.ClipData" AccessPath="[&lt;android.content.ClipData: java.util.ArrayList mItems&gt;, &lt;java.util.ArrayList: java.lang.Object[] array&gt;, &lt;android.content.ClipData$Item: android.net.Uri mUri&gt;]" AccessPathTypes="[java.util.ArrayList, android.content.ClipData$Item[], android.net.Uri]" taintSubFields="true"></to></flow><flow isAlias="true"><from sourceSinkType="Parameter" ParameterIndex="1" BaseType="java.lang.CharSequence"></from><to sourceSinkType="Return" BaseType="android.content.ClipData" AccessPath="[&lt;android.content.ClipData: android.content.ClipDescription mClipDescription&gt;, &lt;android.content.ClipDescription: java.lang.CharSequence mLabel&gt;]" AccessPathTypes="[android.content.ClipDescription, java.lang.CharSequence]" taintSubFields="true"></to></flow><flow isAlias="true"><from sourceSinkType="Return" BaseType="java.lang.String" gap="2"></from><to sourceSinkType="Return" BaseType="android.content.ClipData" AccessPath="[&lt;android.content.ClipData: android.content.ClipDescription mClipDescription&gt;, &lt;android.content.ClipDescription: java.lang.String[] mMimeTypes&gt;]" AccessPathTypes="[android.content.ClipDescription, java.lang.String[]]" taintSubFields="true"></to></flow><flow isAlias="true"><from sourceSinkType="Field" BaseType="android.content.ContentResolver" gap="3"></from><to sourceSinkType="Parameter" ParameterIndex="0" BaseType="android.content.ContentResolver" taintSubFields="true"></to></flow><flow isAlias="true"><from sourceSinkType="Parameter" ParameterIndex="0" BaseType="android.net.Uri" gap="3"></from><to sourceSinkType="Parameter" ParameterIndex="2" BaseType="android.net.Uri" taintSubFields="true"></to></flow><flow isAlias="true"><from sourceSinkType="Return" BaseType="java.lang.String[]" gap="3"></from><to sourceSinkType="Return" BaseType="android.content.ClipData" AccessPath="[&lt;android.content.ClipData: android.content.ClipDescription mClipDescription&gt;, &lt;android.content.ClipDescription: java.lang.String[] mMimeTypes&gt;]" AccessPathTypes="[android.content.ClipDescription, java.lang.String[]]" taintSubFields="true"></to></flow><flow isAlias="true"><from sourceSinkType="Field" BaseType="android.net.Uri" gap="1"></from><to sourceSinkType="Parameter" ParameterIndex="2" BaseType="android.net.Uri" taintSubFields="true"></to></flow><flow isAlias="true"><from sourceSinkType="Field" BaseType="android.net.Uri" gap="1"></from><to sourceSinkType="Parameter" ParameterIndex="0" BaseType="android.net.Uri" gap="2" taintSubFields="true"></to></flow><flow isAlias="true"><from sourceSinkType="Field" BaseType="android.content.ContentResolver" gap="2"></from><to sourceSinkType="GapBaseObject" BaseType="android.content.ContentResolver" gap="3"></to></flow><flow isAlias="true"><from sourceSinkType="Parameter" ParameterIndex="0" BaseType="android.net.Uri" gap="2"></from><to sourceSinkType="Parameter" ParameterIndex="0" BaseType="android.net.Uri" gap="3" taintSubFields="true"></to></flow></flows></method><method id="android.content.ClipData newRawUri(java.lang.CharSequence,android.net.Uri)"><flows><flow isAlias="true"><from sourceSinkType="Parameter" ParameterIndex="1" BaseType="android.net.Uri"></from><to sourceSinkType="Return" BaseType="android.content.ClipData" AccessPath="[&lt;android.content.ClipData: java.util.ArrayList mItems&gt;, &lt;java.util.ArrayList: java.lang.Object[] array&gt;, &lt;android.content.ClipData$Item: android.net.Uri mUri&gt;]" AccessPathTypes="[java.util.ArrayList, android.content.ClipData$Item[], android.net.Uri]" taintSubFields="true"></to></flow><flow isAlias="true"><from sourceSinkType="Parameter" ParameterIndex="0" BaseType="java.lang.CharSequence"></from><to sourceSinkType="Return" BaseType="android.content.ClipData" AccessPath="[&lt;android.content.ClipData: android.content.ClipDescription mClipDescription&gt;, &lt;android.content.ClipDescription: java.lang.CharSequence mLabel&gt;]" AccessPathTypes="[android.content.ClipDescription, java.lang.CharSequence]" taintSubFields="true"></to></flow></flows></method><method id="android.graphics.Bitmap getIcon()"><flows><flow isAlias="true"><from sourceSinkType="Field" BaseType="android.content.ClipData" AccessPath="[&lt;android.content.ClipData: android.graphics.Bitmap mIcon&gt;]" AccessPathTypes="[android.graphics.Bitmap]"></from><to sourceSinkType="Return" BaseType="android.graphics.Bitmap" taintSubFields="true"></to></flow></flows></method><method id="android.content.ClipData$Item getItemAt(int)"><flows><flow isAlias="true"><from sourceSinkType="Field" BaseType="android.content.ClipData" AccessPath="[&lt;android.content.ClipData: java.util.ArrayList mItems&gt;, &lt;java.util.ArrayList: java.lang.Object[] array&gt;]" AccessPathTypes="[java.util.ArrayList, java.lang.Object[]]"></from><to sourceSinkType="Return" BaseType="android.content.ClipData$Item" taintSubFields="true"></to></flow></flows></method><method id="void toShortString(java.lang.StringBuilder)"><flows><flow isAlias="true"><from sourceSinkType="Parameter" ParameterIndex="0" BaseType="java.lang.StringBuilder" AccessPath="[&lt;java.lang.AbstractStringBuilder: int count&gt;]" AccessPathTypes="[int]" gap="4"></from><to sourceSinkType="Field" BaseType="java.lang.StringBuilder" AccessPath="[&lt;java.lang.AbstractStringBuilder: char[] value&gt;]" AccessPathTypes="[char[]]" gap="7" taintSubFields="true"></to></flow><flow isAlias="true"><from sourceSinkType="Parameter" ParameterIndex="0" BaseType="java.lang.StringBuilder" AccessPath="[&lt;java.lang.AbstractStringBuilder: int count&gt;]" AccessPathTypes="[int]"></from><to sourceSinkType="Field" BaseType="java.lang.StringBuilder" AccessPath="[&lt;java.lang.AbstractStringBuilder: char[] value&gt;]" AccessPathTypes="[char[]]" gap="7" taintSubFields="true"></to></flow><flow isAlias="true"><from sourceSinkType="Parameter" ParameterIndex="0" BaseType="java.lang.StringBuilder" AccessPath="[&lt;java.lang.AbstractStringBuilder: int count&gt;]" AccessPathTypes="[int]" gap="7"></from><to sourceSinkType="Field" BaseType="java.lang.StringBuilder" AccessPath="[&lt;java.lang.AbstractStringBuilder: char[] value&gt;]" AccessPathTypes="[char[]]" gap="4" taintSubFields="true"></to></flow><flow isAlias="true"><from sourceSinkType="Parameter" ParameterIndex="0" BaseType="java.lang.StringBuilder" AccessPath="[&lt;java.lang.AbstractStringBuilder: int count&gt;]" AccessPathTypes="[int]" gap="7"></from><to sourceSinkType="Field" BaseType="java.lang.StringBuilder" AccessPath="[&lt;java.lang.AbstractStringBuilder: int count&gt;]" AccessPathTypes="[int]" gap="7" taintSubFields="true"></to></flow><flow isAlias="true"><from sourceSinkType="Parameter" ParameterIndex="0" BaseType="java.lang.StringBuilder" AccessPath="[&lt;java.lang.AbstractStringBuilder: int count&gt;]" AccessPathTypes="[int]" gap="4"></from><to sourceSinkType="Field" BaseType="java.lang.StringBuilder" AccessPath="[&lt;java.lang.AbstractStringBuilder: char[] value&gt;]" AccessPathTypes="[char[]]" gap="4" taintSubFields="true"></to></flow><flow isAlias="true"><from sourceSinkType="Parameter" ParameterIndex="0" BaseType="java.lang.StringBuilder" AccessPath="[&lt;java.lang.AbstractStringBuilder: char[] value&gt;]" AccessPathTypes="[char[]]" gap="4"></from><to sourceSinkType="Field" BaseType="java.lang.StringBuilder" AccessPath="[&lt;java.lang.AbstractStringBuilder: char[] value&gt;]" AccessPathTypes="[char[]]" gap="4" taintSubFields="true"></to></flow><flow isAlias="true"><from sourceSinkType="Parameter" ParameterIndex="0" BaseType="java.lang.StringBuilder" AccessPath="[&lt;java.lang.AbstractStringBuilder: int count&gt;]" AccessPathTypes="[int]"></from><to sourceSinkType="Parameter" ParameterIndex="0" BaseType="java.lang.StringBuilder" AccessPath="[&lt;java.lang.AbstractStringBuilder: int count&gt;]" AccessPathTypes="[int]" gap="7" taintSubFields="true"></to></flow><flow isAlias="true"><from sourceSinkType="Parameter" ParameterIndex="0" BaseType="java.lang.StringBuilder" AccessPath="[&lt;java.lang.AbstractStringBuilder: int count&gt;]" AccessPathTypes="[int]" gap="7"></from><to sourceSinkType="Parameter" ParameterIndex="0" BaseType="java.lang.StringBuilder" AccessPath="[&lt;java.lang.AbstractStringBuilder: int count&gt;]" AccessPathTypes="[int]" taintSubFields="true"></to></flow><flow isAlias="true"><from sourceSinkType="Parameter" ParameterIndex="0" BaseType="java.lang.StringBuilder" AccessPath="[&lt;java.lang.AbstractStringBuilder: char[] value&gt;]" AccessPathTypes="[char[]]"></from><to sourceSinkType="Parameter" ParameterIndex="0" BaseType="java.lang.StringBuilder" AccessPath="[&lt;java.lang.AbstractStringBuilder: char[] value&gt;]" AccessPathTypes="[char[]]" gap="7" taintSubFields="true"></to></flow><flow isAlias="true"><from sourceSinkType="Parameter" ParameterIndex="0" BaseType="java.lang.StringBuilder" AccessPath="[&lt;java.lang.AbstractStringBuilder: char[] value&gt;]" AccessPathTypes="[char[]]" gap="7"></from><to sourceSinkType="Parameter" ParameterIndex="0" BaseType="java.lang.StringBuilder" AccessPath="[&lt;java.lang.AbstractStringBuilder: char[] value&gt;]" AccessPathTypes="[char[]]" taintSubFields="true"></to></flow><flow isAlias="true"><from sourceSinkType="Parameter" ParameterIndex="0" BaseType="java.lang.StringBuilder" AccessPath="[&lt;java.lang.AbstractStringBuilder: int count&gt;]" AccessPathTypes="[int]" gap="7"></from><to sourceSinkType="Field" BaseType="java.lang.StringBuilder" AccessPath="[&lt;java.lang.AbstractStringBuilder: int count&gt;]" AccessPathTypes="[int]" gap="4" taintSubFields="true"></to></flow><flow isAlias="true"><from sourceSinkType="Parameter" ParameterIndex="0" BaseType="java.lang.StringBuilder" AccessPath="[&lt;java.lang.AbstractStringBuilder: int count&gt;]" AccessPathTypes="[int]" gap="4"></from><to sourceSinkType="Field" BaseType="java.lang.StringBuilder" AccessPath="[&lt;java.lang.AbstractStringBuilder: int count&gt;]" AccessPathTypes="[int]" gap="7" taintSubFields="true"></to></flow><flow isAlias="true"><from sourceSinkType="Field" BaseType="android.graphics.Bitmap" gap="5"></from><to sourceSinkType="Field" BaseType="android.content.ClipData" AccessPath="[&lt;android.content.ClipData: android.graphics.Bitmap mIcon&gt;]" AccessPathTypes="[android.graphics.Bitmap]" taintSubFields="true"></to></flow><flow isAlias="true"><from sourceSinkType="Field" BaseType="android.content.ClipData" AccessPath="[&lt;android.content.ClipData: android.graphics.Bitmap mIcon&gt;]" AccessPathTypes="[android.graphics.Bitmap]"></from><to sourceSinkType="GapBaseObject" BaseType="android.graphics.Bitmap" gap="5"></to></flow><flow isAlias="true"><from sourceSinkType="Parameter" ParameterIndex="0" BaseType="java.lang.StringBuilder" AccessPath="[&lt;java.lang.AbstractStringBuilder: int count&gt;]" AccessPathTypes="[int]"></from><to sourceSinkType="Field" BaseType="java.lang.StringBuilder" AccessPath="[&lt;java.lang.AbstractStringBuilder: char[] value&gt;]" AccessPathTypes="[char[]]" gap="4" taintSubFields="true"></to></flow><flow isAlias="true"><from sourceSinkType="Parameter" ParameterIndex="0" BaseType="java.lang.StringBuilder" AccessPath="[&lt;java.lang.AbstractStringBuilder: char[] value&gt;]" AccessPathTypes="[char[]]" gap="7"></from><to sourceSinkType="Field" BaseType="java.lang.StringBuilder" AccessPath="[&lt;java.lang.AbstractStringBuilder: char[] value&gt;]" AccessPathTypes="[char[]]" gap="4" taintSubFields="true"></to></flow><flow isAlias="true"><from sourceSinkType="Parameter" ParameterIndex="0" BaseType="java.lang.StringBuilder" AccessPath="[&lt;java.lang.AbstractStringBuilder: char[] value&gt;]" AccessPathTypes="[char[]]" gap="4"></from><to sourceSinkType="Field" BaseType="java.lang.StringBuilder" AccessPath="[&lt;java.lang.AbstractStringBuilder: char[] value&gt;]" AccessPathTypes="[char[]]" gap="7" taintSubFields="true"></to></flow><flow isAlias="true"><from sourceSinkType="Parameter" ParameterIndex="0" BaseType="java.lang.StringBuilder" AccessPath="[&lt;java.lang.AbstractStringBuilder: int count&gt;]" AccessPathTypes="[int]" gap="4"></from><to sourceSinkType="Parameter" ParameterIndex="0" BaseType="java.lang.StringBuilder" AccessPath="[&lt;java.lang.AbstractStringBuilder: char[] value&gt;]" AccessPathTypes="[char[]]" gap="7" taintSubFields="true"></to></flow><flow isAlias="true"><from sourceSinkType="Parameter" ParameterIndex="0" BaseType="java.lang.StringBuilder" AccessPath="[&lt;java.lang.AbstractStringBuilder: int count&gt;]" AccessPathTypes="[int]"></from><to sourceSinkType="Parameter" ParameterIndex="0" BaseType="java.lang.StringBuilder" AccessPath="[&lt;java.lang.AbstractStringBuilder: char[] value&gt;]" AccessPathTypes="[char[]]" gap="7" taintSubFields="true"></to></flow><flow isAlias="true"><from sourceSinkType="Parameter" ParameterIndex="0" BaseType="java.lang.StringBuilder" AccessPath="[&lt;java.lang.AbstractStringBuilder: int count&gt;]" AccessPathTypes="[int]" gap="7"></from><to sourceSinkType="Parameter" ParameterIndex="0" BaseType="java.lang.StringBuilder" AccessPath="[&lt;java.lang.AbstractStringBuilder: char[] value&gt;]" AccessPathTypes="[char[]]" taintSubFields="true"></to></flow><flow isAlias="true"><from sourceSinkType="Parameter" ParameterIndex="0" BaseType="java.lang.StringBuilder" AccessPath="[&lt;java.lang.AbstractStringBuilder: char[] value&gt;]" AccessPathTypes="[char[]]" gap="7"></from><to sourceSinkType="Field" BaseType="java.lang.StringBuilder" AccessPath="[&lt;java.lang.AbstractStringBuilder: char[] value&gt;]" AccessPathTypes="[char[]]" gap="7" taintSubFields="true"></to></flow><flow isAlias="true"><from sourceSinkType="Field" BaseType="android.content.ClipDescription" gap="4"></from><to sourceSinkType="Field" BaseType="android.content.ClipData" AccessPath="[&lt;android.content.ClipData: android.content.ClipDescription mClipDescription&gt;]" AccessPathTypes="[android.content.ClipDescription]" taintSubFields="true"></to></flow><flow isAlias="true"><from sourceSinkType="Field" BaseType="android.graphics.Bitmap" gap="5"></from><to sourceSinkType="GapBaseObject" BaseType="android.graphics.Bitmap" gap="6"></to></flow><flow isAlias="true"><from sourceSinkType="Field" BaseType="android.content.ClipData" AccessPath="[&lt;android.content.ClipData: android.graphics.Bitmap mIcon&gt;]" AccessPathTypes="[android.graphics.Bitmap]"></from><to sourceSinkType="GapBaseObject" BaseType="android.graphics.Bitmap" gap="6"></to></flow><flow isAlias="true"><from sourceSinkType="Parameter" ParameterIndex="0" BaseType="java.lang.StringBuilder" AccessPath="[&lt;java.lang.AbstractStringBuilder: int count&gt;]" AccessPathTypes="[int]" gap="4"></from><to sourceSinkType="Field" BaseType="java.lang.StringBuilder" AccessPath="[&lt;java.lang.AbstractStringBuilder: int count&gt;]" AccessPathTypes="[int]" gap="4" taintSubFields="true"></to></flow><flow isAlias="true"><from sourceSinkType="Parameter" ParameterIndex="0" BaseType="java.lang.StringBuilder" AccessPath="[&lt;java.lang.AbstractStringBuilder: int count&gt;]" AccessPathTypes="[int]" gap="7"></from><to sourceSinkType="Parameter" ParameterIndex="0" BaseType="java.lang.StringBuilder" AccessPath="[&lt;java.lang.AbstractStringBuilder: char[] value&gt;]" AccessPathTypes="[char[]]" gap="7" taintSubFields="true"></to></flow><flow isAlias="true"><from sourceSinkType="Parameter" ParameterIndex="0" BaseType="java.lang.StringBuilder" AccessPath="[&lt;java.lang.AbstractStringBuilder: char[] value&gt;]" AccessPathTypes="[char[]]"></from><to sourceSinkType="Field" BaseType="java.lang.StringBuilder" AccessPath="[&lt;java.lang.AbstractStringBuilder: char[] value&gt;]" AccessPathTypes="[char[]]" gap="7" taintSubFields="true"></to></flow><flow isAlias="true"><from sourceSinkType="Field" BaseType="android.content.ClipData" AccessPath="[&lt;android.content.ClipData: java.util.ArrayList mItems&gt;, &lt;java.util.ArrayList: java.lang.Object[] array&gt;]" AccessPathTypes="[java.util.ArrayList, java.lang.Object[]]"></from><to sourceSinkType="GapBaseObject" BaseType="android.content.ClipData$Item" gap="7"></to></flow><flow isAlias="true"><from sourceSinkType="Parameter" ParameterIndex="0" BaseType="java.lang.StringBuilder" AccessPath="[&lt;java.lang.AbstractStringBuilder: int count&gt;]" AccessPathTypes="[int]"></from><to sourceSinkType="Parameter" ParameterIndex="0" BaseType="java.lang.StringBuilder" AccessPath="[&lt;java.lang.AbstractStringBuilder: char[] value&gt;]" AccessPathTypes="[char[]]" taintSubFields="true"></to></flow><flow isAlias="true"><from sourceSinkType="Field" BaseType="android.graphics.Bitmap" gap="6"></from><to sourceSinkType="Field" BaseType="android.content.ClipData" AccessPath="[&lt;android.content.ClipData: android.graphics.Bitmap mIcon&gt;]" AccessPathTypes="[android.graphics.Bitmap]" taintSubFields="true"></to></flow><flow isAlias="true"><from sourceSinkType="Parameter" ParameterIndex="0" BaseType="java.lang.StringBuilder" AccessPath="[&lt;java.lang.AbstractStringBuilder: char[] value&gt;]" AccessPathTypes="[char[]]" gap="4"></from><to sourceSinkType="Parameter" ParameterIndex="0" BaseType="java.lang.StringBuilder" AccessPath="[&lt;java.lang.AbstractStringBuilder: char[] value&gt;]" AccessPathTypes="[char[]]" gap="7" taintSubFields="true"></to></flow><flow isAlias="true"><from sourceSinkType="Parameter" ParameterIndex="0" BaseType="java.lang.StringBuilder" AccessPath="[&lt;java.lang.AbstractStringBuilder: int count&gt;]" AccessPathTypes="[int]"></from><to sourceSinkType="Field" BaseType="java.lang.StringBuilder" AccessPath="[&lt;java.lang.AbstractStringBuilder: int count&gt;]" AccessPathTypes="[int]" gap="7" taintSubFields="true"></to></flow><flow isAlias="true"><from sourceSinkType="Parameter" ParameterIndex="0" BaseType="java.lang.StringBuilder" AccessPath="[&lt;java.lang.AbstractStringBuilder: int count&gt;]" AccessPathTypes="[int]" gap="7"></from><to sourceSinkType="Field" BaseType="java.lang.StringBuilder" AccessPath="[&lt;java.lang.AbstractStringBuilder: char[] value&gt;]" AccessPathTypes="[char[]]" gap="7" taintSubFields="true"></to></flow><flow isAlias="true"><from sourceSinkType="Field" BaseType="android.content.ClipData" AccessPath="[&lt;android.content.ClipData: android.content.ClipDescription mClipDescription&gt;]" AccessPathTypes="[android.content.ClipDescription]"></from><to sourceSinkType="GapBaseObject" BaseType="android.content.ClipDescription" gap="4"></to></flow><flow isAlias="true"><from sourceSinkType="Parameter" ParameterIndex="0" BaseType="java.lang.StringBuilder"></from><to sourceSinkType="Parameter" ParameterIndex="0" BaseType="java.lang.StringBuilder" gap="4" taintSubFields="true"></to></flow><flow isAlias="true"><from sourceSinkType="Parameter" ParameterIndex="0" BaseType="java.lang.StringBuilder" AccessPath="[&lt;java.lang.AbstractStringBuilder: char[] value&gt;]" AccessPathTypes="[char[]]"></from><to sourceSinkType="Field" BaseType="java.lang.StringBuilder" AccessPath="[&lt;java.lang.AbstractStringBuilder: char[] value&gt;]" AccessPathTypes="[char[]]" gap="4" taintSubFields="true"></to></flow><flow isAlias="true"><from sourceSinkType="Parameter" ParameterIndex="0" BaseType="java.lang.StringBuilder" AccessPath="[&lt;java.lang.AbstractStringBuilder: int count&gt;]" AccessPathTypes="[int]"></from><to sourceSinkType="Field" BaseType="java.lang.StringBuilder" AccessPath="[&lt;java.lang.AbstractStringBuilder: int count&gt;]" AccessPathTypes="[int]" gap="4" taintSubFields="true"></to></flow><flow isAlias="true"><from sourceSinkType="Field" BaseType="android.content.ClipData$Item" gap="7"></from><to sourceSinkType="Field" BaseType="android.content.ClipData" AccessPath="[&lt;android.content.ClipData: java.util.ArrayList mItems&gt;, &lt;java.util.ArrayList: java.lang.Object[] array&gt;]" AccessPathTypes="[java.util.ArrayList, java.lang.Object[]]" taintSubFields="true"></to></flow><flow isAlias="true"><from sourceSinkType="Parameter" ParameterIndex="0" BaseType="java.lang.StringBuilder" AccessPath="[&lt;java.lang.AbstractStringBuilder: int count&gt;]" AccessPathTypes="[int]" gap="4"></from><to sourceSinkType="Parameter" ParameterIndex="0" BaseType="java.lang.StringBuilder" AccessPath="[&lt;java.lang.AbstractStringBuilder: int count&gt;]" AccessPathTypes="[int]" gap="7" taintSubFields="true"></to></flow><flow isAlias="true"><from sourceSinkType="Parameter" ParameterIndex="0" BaseType="java.lang.StringBuilder" AccessPath="[&lt;java.lang.AbstractStringBuilder: int count&gt;]" AccessPathTypes="[int]" gap="4"></from><to sourceSinkType="Parameter" ParameterIndex="0" BaseType="java.lang.StringBuilder" AccessPath="[&lt;java.lang.AbstractStringBuilder: char[] value&gt;]" AccessPathTypes="[char[]]" taintSubFields="true"></to></flow></flows></method><method id="java.lang.Object clone()"><flows><flow isAlias="true"><from sourceSinkType="Field" BaseType="java.lang.Object"></from><to sourceSinkType="Return" BaseType="java.lang.Object" taintSubFields="true"></to></flow></flows></method><method id="int getItemCount()"><flows><flow isAlias="true"><from sourceSinkType="Field" BaseType="android.content.ClipData" AccessPath="[&lt;android.content.ClipData: java.util.ArrayList mItems&gt;, &lt;java.util.ArrayList: int size&gt;]" AccessPathTypes="[java.util.ArrayList, int]"></from><to sourceSinkType="Return" BaseType="int" taintSubFields="true"></to></flow></flows></method><method id="android.content.ClipData newHtmlText(java.lang.CharSequence,java.lang.CharSequence,java.lang.String)"><flows><flow isAlias="true"><from sourceSinkType="Parameter" ParameterIndex="1" BaseType="java.lang.CharSequence"></from><to sourceSinkType="Return" BaseType="android.content.ClipData" AccessPath="[&lt;android.content.ClipData: java.util.ArrayList mItems&gt;, &lt;java.util.ArrayList: java.lang.Object[] array&gt;, &lt;android.content.ClipData$Item: java.lang.CharSequence mText&gt;]" AccessPathTypes="[java.util.ArrayList, android.content.ClipData$Item[], java.lang.CharSequence]" taintSubFields="true"></to></flow><flow isAlias="true"><from sourceSinkType="Parameter" ParameterIndex="0" BaseType="java.lang.CharSequence"></from><to sourceSinkType="Return" BaseType="android.content.ClipData" AccessPath="[&lt;android.content.ClipData: android.content.ClipDescription mClipDescription&gt;, &lt;android.content.ClipDescription: java.lang.CharSequence mLabel&gt;]" AccessPathTypes="[android.content.ClipDescription, java.lang.CharSequence]" taintSubFields="true"></to></flow><flow isAlias="true"><from sourceSinkType="Parameter" ParameterIndex="2" BaseType="java.lang.String"></from><to sourceSinkType="Return" BaseType="android.content.ClipData" AccessPath="[&lt;android.content.ClipData: java.util.ArrayList mItems&gt;, &lt;java.util.ArrayList: java.lang.Object[] array&gt;, &lt;android.content.ClipData$Item: java.lang.String mHtmlText&gt;]" AccessPathTypes="[java.util.ArrayList, android.content.ClipData$Item[], java.lang.String]" taintSubFields="true"></to></flow></flows></method><method id="void writeToParcel(android.os.Parcel,int)"><flows><flow isAlias="true"><from sourceSinkType="Field" BaseType="android.os.Parcel" gap="15"></from><to sourceSinkType="GapBaseObject" BaseType="android.os.Parcel" gap="20"></to></flow><flow isAlias="true"><from sourceSinkType="Field" BaseType="android.os.Parcel" gap="18"></from><to sourceSinkType="Parameter" ParameterIndex="0" BaseType="android.os.Parcel" gap="23" taintSubFields="true"></to></flow><flow isAlias="true"><from sourceSinkType="Field" BaseType="java.lang.CharSequence" gap="35"></from><to sourceSinkType="Field" BaseType="android.content.ClipData" AccessPath="[&lt;android.content.ClipData: java.util.ArrayList mItems&gt;, &lt;java.util.ArrayList: java.lang.Object[] array&gt;, &lt;android.content.ClipData$Item: java.lang.CharSequence mText&gt;]" AccessPathTypes="[java.util.ArrayList, java.lang.Object[], java.lang.CharSequence]" taintSubFields="true"></to></flow><flow isAlias="true"><from sourceSinkType="Field" BaseType="java.lang.CharSequence" gap="29"></from><to sourceSinkType="GapBaseObject" BaseType="java.lang.CharSequence" gap="31"></to></flow><flow isAlias="true"><from sourceSinkType="Field" BaseType="java.lang.CharSequence" gap="31"></from><to sourceSinkType="GapBaseObject" BaseType="java.lang.CharSequence" gap="29"></to></flow><flow isAlias="true"><from sourceSinkType="Field" BaseType="android.os.Parcel" gap="19"></from><to sourceSinkType="GapBaseObject" BaseType="android.os.Parcel" gap="24"></to></flow><flow isAlias="true"><from sourceSinkType="Field" BaseType="android.text.Spanned" gap="41"></from><to sourceSinkType="GapBaseObject" BaseType="java.lang.CharSequence" gap="31"></to></flow><flow isAlias="true"><from sourceSinkType="Parameter" ParameterIndex="0" BaseType="android.os.Parcel"></from><to sourceSinkType="Parameter" ParameterIndex="0" BaseType="android.os.Parcel" gap="12" taintSubFields="true"></to></flow><flow isAlias="true"><from sourceSinkType="Field" BaseType="android.os.Parcel" gap="15"></from><to sourceSinkType="GapBaseObject" BaseType="android.os.Parcel" gap="32"></to></flow><flow isAlias="true"><from sourceSinkType="Field" BaseType="android.os.Parcel" gap="24"></from><to sourceSinkType="Parameter" ParameterIndex="0" BaseType="android.os.Parcel" gap="28" taintSubFields="true"></to></flow><flow isAlias="true"><from sourceSinkType="Field" BaseType="android.os.Parcel" gap="16"></from><to sourceSinkType="GapBaseObject" BaseType="android.os.Parcel" gap="15"></to></flow><flow isAlias="true"><from sourceSinkType="Field" BaseType="android.text.Spanned" gap="43"></from><to sourceSinkType="GapBaseObject" BaseType="java.lang.CharSequence" gap="31"></to></flow><flow isAlias="true"><from sourceSinkType="Parameter" ParameterIndex="0" BaseType="android.os.Parcel" gap="12"></from><to sourceSinkType="GapBaseObject" BaseType="android.os.Parcel" gap="13"></to></flow><flow isAlias="true"><from sourceSinkType="Field" BaseType="android.os.Parcel" gap="34"></from><to sourceSinkType="GapBaseObject" BaseType="android.os.Parcel" gap="37"></to></flow><flow isAlias="true"><from sourceSinkType="Parameter" ParameterIndex="0" BaseType="android.os.Parcel" gap="28"></from><to sourceSinkType="GapBaseObject" BaseType="android.os.Parcel" gap="20"></to></flow><flow isAlias="true"><from sourceSinkType="Field" BaseType="android.text.Spanned" gap="36"></from><to sourceSinkType="GapBaseObject" BaseType="android.text.Spanned" gap="41"></to></flow><flow isAlias="true"><from sourceSinkType="Parameter" ParameterIndex="1" BaseType="int" gap="12"></from><to sourceSinkType="Parameter" ParameterIndex="1" BaseType="int" gap="33" taintSubFields="true"></to></flow><flow isAlias="true"><from sourceSinkType="Parameter" ParameterIndex="1" BaseType="int" gap="23"></from><to sourceSinkType="Parameter" ParameterIndex="1" BaseType="int" gap="33" taintSubFields="true"></to></flow><flow isAlias="true"><from sourceSinkType="Parameter" ParameterIndex="0" BaseType="android.os.Parcel" gap="28"></from><to sourceSinkType="GapBaseObject" BaseType="android.os.Parcel" gap="32"></to></flow><flow isAlias="true"><from sourceSinkType="Field" BaseType="android.os.Parcel" gap="15"></from><to sourceSinkType="Parameter" ParameterIndex="0" BaseType="android.os.Parcel" taintSubFields="true"></to></flow><flow isAlias="true"><from sourceSinkType="Field" BaseType="android.os.Parcel" gap="17"></from><to sourceSinkType="GapBaseObject" BaseType="android.os.Parcel" gap="18"></to></flow><flow isAlias="true"><from sourceSinkType="Parameter" ParameterIndex="0" BaseType="android.os.Parcel" gap="23"></from><to sourceSinkType="GapBaseObject" BaseType="android.os.Parcel" gap="25"></to></flow><flow isAlias="true"><from sourceSinkType="Field" BaseType="android.os.Parcel" gap="15"></from><to sourceSinkType="GapBaseObject" BaseType="android.os.Parcel" gap="21"></to></flow><flow isAlias="true"><from sourceSinkType="Field" BaseType="java.lang.CharSequence" gap="29"></from><to sourceSinkType="GapBaseObject" BaseType="android.text.Spanned" gap="36"></to></flow><flow isAlias="true"><from sourceSinkType="Field" BaseType="android.text.Spanned" gap="36"></from><to sourceSinkType="GapBaseObject" BaseType="java.lang.CharSequence" gap="29"></to></flow><flow isAlias="true"><from sourceSinkType="Field" BaseType="android.os.Parcel" gap="19"></from><to sourceSinkType="GapBaseObject" BaseType="android.os.Parcel" gap="25"></to></flow><flow isAlias="true"><from sourceSinkType="Field" BaseType="android.text.Spanned" gap="42"></from><to sourceSinkType="Field" BaseType="android.content.ClipData" AccessPath="[&lt;android.content.ClipData: java.util.ArrayList mItems&gt;, &lt;java.util.ArrayList: java.lang.Object[] array&gt;, &lt;android.content.ClipData$Item: java.lang.CharSequence mText&gt;]" AccessPathTypes="[java.util.ArrayList, java.lang.Object[], android.text.Spanned]" taintSubFields="true"></to></flow><flow isAlias="true"><from sourceSinkType="Field" BaseType="android.os.Parcel" gap="13"></from><to sourceSinkType="Parameter" ParameterIndex="0" BaseType="android.os.Parcel" gap="14" taintSubFields="true"></to></flow><flow isAlias="true"><from sourceSinkType="Parameter" ParameterIndex="1" BaseType="int" gap="14"></from><to sourceSinkType="Parameter" ParameterIndex="1" BaseType="int" gap="33" taintSubFields="true"></to></flow><flow isAlias="true"><from sourceSinkType="Return" BaseType="java.lang.Object[]" gap="36"></from><to sourceSinkType="GapBaseObject" BaseType="android.text.style.CharacterStyle" gap="39"></to></flow><flow isAlias="true"><from sourceSinkType="Field" BaseType="android.text.style.CharacterStyle" gap="39"></from><to sourceSinkType="Parameter" ParameterIndex="0" BaseType="android.text.style.CharacterStyle" gap="41" taintSubFields="true"></to></flow><flow isAlias="true"><from sourceSinkType="Field" BaseType="android.content.ClipData" AccessPath="[&lt;android.content.ClipData: android.graphics.Bitmap mIcon&gt;]" AccessPathTypes="[android.graphics.Bitmap]"></from><to sourceSinkType="GapBaseObject" BaseType="android.graphics.Bitmap" gap="14"></to></flow><flow isAlias="true"><from sourceSinkType="Field" BaseType="android.graphics.Bitmap" gap="14"></from><to sourceSinkType="Field" BaseType="android.content.ClipData" AccessPath="[&lt;android.content.ClipData: android.graphics.Bitmap mIcon&gt;]" AccessPathTypes="[android.graphics.Bitmap]" taintSubFields="true"></to></flow><flow isAlias="true"><from sourceSinkType="Field" BaseType="java.lang.CharSequence" gap="31"></from><to sourceSinkType="Field" BaseType="android.content.ClipData" AccessPath="[&lt;android.content.ClipData: java.util.ArrayList mItems&gt;, &lt;java.util.ArrayList: java.lang.Object[] array&gt;, &lt;android.content.ClipData$Item: java.lang.CharSequence mText&gt;]" AccessPathTypes="[java.util.ArrayList, java.lang.Object[], java.lang.CharSequence]" taintSubFields="true"></to></flow><flow isAlias="true"><from sourceSinkType="Field" BaseType="android.os.Parcel" gap="25"></from><to sourceSinkType="GapBaseObject" BaseType="android.os.Parcel" gap="17"></to></flow><flow isAlias="true"><from sourceSinkType="Field" BaseType="android.os.Parcel" gap="20"></from><to sourceSinkType="GapBaseObject" BaseType="android.os.Parcel" gap="22"></to></flow><flow isAlias="true"><from sourceSinkType="Field" BaseType="android.os.Parcel" gap="22"></from><to sourceSinkType="GapBaseObject" BaseType="android.os.Parcel" gap="32"></to></flow><flow isAlias="true"><from sourceSinkType="Parameter" ParameterIndex="0" BaseType="android.os.Parcel" gap="28"></from><to sourceSinkType="GapBaseObject" BaseType="android.os.Parcel" gap="21"></to></flow><flow isAlias="true"><from sourceSinkType="Field" BaseType="android.os.Parcel" gap="32"></from><to sourceSinkType="Parameter" ParameterIndex="0" BaseType="android.os.Parcel" gap="33" taintSubFields="true"></to></flow><flow isAlias="true"><from sourceSinkType="Field" BaseType="android.content.Intent" gap="23"></from><to sourceSinkType="Field" BaseType="android.content.ClipData" AccessPath="[&lt;android.content.ClipData: java.util.ArrayList mItems&gt;, &lt;java.util.ArrayList: java.lang.Object[] array&gt;, &lt;android.content.ClipData$Item: android.content.Intent mIntent&gt;]" AccessPathTypes="[java.util.ArrayList, java.lang.Object[], android.content.Intent]" taintSubFields="true"></to></flow><flow isAlias="true"><from sourceSinkType="Field" BaseType="android.text.Spanned" gap="42"></from><to sourceSinkType="GapBaseObject" BaseType="java.lang.CharSequence" gap="31"></to></flow><flow isAlias="true"><from sourceSinkType="Field" BaseType="android.text.ParcelableSpan" gap="33"></from><to sourceSinkType="Parameter" ParameterIndex="0" BaseType="android.text.ParcelableSpan" gap="41" taintSubFields="true"></to></flow><flow isAlias="true"><from sourceSinkType="Parameter" ParameterIndex="0" BaseType="java.lang.Object" gap="41"></from><to sourceSinkType="GapBaseObject" BaseType="android.text.ParcelableSpan" gap="40"></to></flow><flow isAlias="true"><from sourceSinkType="Parameter" ParameterIndex="0" BaseType="android.os.Parcel" gap="33"></from><to sourceSinkType="GapBaseObject" BaseType="android.os.Parcel" gap="32"></to></flow><flow isAlias="true"><from sourceSinkType="Field" BaseType="android.content.ClipData" AccessPath="[&lt;android.content.ClipData: java.util.ArrayList mItems&gt;, &lt;java.util.ArrayList: java.lang.Object[] array&gt;, &lt;android.content.ClipData$Item: java.lang.CharSequence mText&gt;]" AccessPathTypes="[java.util.ArrayList, java.lang.Object[], java.lang.CharSequence]"></from><to sourceSinkType="GapBaseObject" BaseType="java.lang.CharSequence" gap="31"></to></flow><flow isAlias="true"><from sourceSinkType="Parameter" ParameterIndex="1" BaseType="int" gap="28"></from><to sourceSinkType="Parameter" ParameterIndex="1" BaseType="int" gap="33" taintSubFields="true"></to></flow><flow isAlias="true"><from sourceSinkType="Field" BaseType="java.lang.CharSequence" gap="29"></from><to sourceSinkType="GapBaseObject" BaseType="java.lang.CharSequence" gap="35"></to></flow><flow isAlias="true"><from sourceSinkType="Field" BaseType="java.lang.CharSequence" gap="35"></from><to sourceSinkType="GapBaseObject" BaseType="java.lang.CharSequence" gap="29"></to></flow><flow isAlias="true"><from sourceSinkType="Field" BaseType="android.content.ClipData" AccessPath="[&lt;android.content.ClipData: java.util.ArrayList mItems&gt;, &lt;java.util.ArrayList: java.lang.Object[] array&gt;, &lt;android.content.ClipData$Item: android.content.Intent mIntent&gt;]" AccessPathTypes="[java.util.ArrayList, java.lang.Object[], android.content.Intent]"></from><to sourceSinkType="GapBaseObject" BaseType="android.content.Intent" gap="23"></to></flow><flow isAlias="true"><from sourceSinkType="Field" BaseType="android.content.ClipData" AccessPath="[&lt;android.content.ClipData: android.content.ClipDescription mClipDescription&gt;]" AccessPathTypes="[android.content.ClipDescription]"></from><to sourceSinkType="GapBaseObject" BaseType="android.content.ClipDescription" gap="12"></to></flow><flow isAlias="true"><from sourceSinkType="Field" BaseType="android.text.ParcelableSpan" gap="40"></from><to sourceSinkType="Parameter" ParameterIndex="0" BaseType="android.text.ParcelableSpan" gap="42" taintSubFields="true"></to></flow><flow isAlias="true"><from sourceSinkType="Field" BaseType="android.text.ParcelableSpan" gap="40"></from><to sourceSinkType="Parameter" ParameterIndex="0" BaseType="android.text.ParcelableSpan" gap="43" taintSubFields="true"></to></flow><flow isAlias="true"><from sourceSinkType="Field" BaseType="android.os.Parcel" gap="25"></from><to sourceSinkType="GapBaseObject" BaseType="android.os.Parcel" gap="20"></to></flow><flow isAlias="true"><from sourceSinkType="Field" BaseType="android.content.ClipData" AccessPath="[&lt;android.content.ClipData: java.util.ArrayList mItems&gt;, &lt;java.util.ArrayList: java.lang.Object[] array&gt;, &lt;android.content.ClipData$Item: android.net.Uri mUri&gt;]" AccessPathTypes="[java.util.ArrayList, java.lang.Object[], android.net.Uri]"></from><to sourceSinkType="GapBaseObject" BaseType="android.net.Uri" gap="28"></to></flow><flow isAlias="true"><from sourceSinkType="Field" BaseType="android.text.Spanned" gap="41"></from><to sourceSinkType="GapBaseObject" BaseType="java.lang.CharSequence" gap="29"></to></flow><flow isAlias="true"><from sourceSinkType="Field" BaseType="android.text.Spanned" gap="43"></from><to sourceSinkType="GapBaseObject" BaseType="java.lang.CharSequence" gap="29"></to></flow><flow isAlias="true"><from sourceSinkType="Field" BaseType="android.text.Spanned" gap="36"></from><to sourceSinkType="Field" BaseType="android.content.ClipData" AccessPath="[&lt;android.content.ClipData: java.util.ArrayList mItems&gt;, &lt;java.util.ArrayList: java.lang.Object[] array&gt;, &lt;android.content.ClipData$Item: java.lang.CharSequence mText&gt;]" AccessPathTypes="[java.util.ArrayList, java.lang.Object[], android.text.Spanned]" taintSubFields="true"></to></flow><flow isAlias="true"><from sourceSinkType="Parameter" ParameterIndex="0" BaseType="java.lang.Object" gap="41"></from><to sourceSinkType="GapBaseObject" BaseType="android.text.style.CharacterStyle" gap="39"></to></flow><flow isAlias="true"><from sourceSinkType="Field" BaseType="android.os.Parcel" gap="25"></from><to sourceSinkType="Parameter" ParameterIndex="0" BaseType="android.os.Parcel" taintSubFields="true"></to></flow><flow isAlias="true"><from sourceSinkType="Parameter" ParameterIndex="0" BaseType="java.lang.Object" gap="42"></from><to sourceSinkType="Parameter" ParameterIndex="0" BaseType="java.lang.Object" gap="43" taintSubFields="true"></to></flow><flow isAlias="true"><from sourceSinkType="Return" BaseType="java.lang.Object" gap="39"></from><to sourceSinkType="GapBaseObject" BaseType="android.text.ParcelableSpan" gap="40"></to></flow><flow isAlias="true"><from sourceSinkType="Field" BaseType="android.content.ClipData" AccessPath="[&lt;android.content.ClipData: java.util.ArrayList mItems&gt;, &lt;java.util.ArrayList: java.lang.Object[] array&gt;, &lt;android.content.ClipData$Item: java.lang.String mHtmlText&gt;]" AccessPathTypes="[java.util.ArrayList, java.lang.Object[], java.lang.String]"></from><to sourceSinkType="Parameter" ParameterIndex="0" BaseType="java.lang.String" gap="17" taintSubFields="true"></to></flow><flow isAlias="true"><from sourceSinkType="Field" BaseType="android.text.Spanned" gap="42"></from><to sourceSinkType="GapBaseObject" BaseType="android.text.Spanned" gap="43"></to></flow><flow isAlias="true"><from sourceSinkType="Field" BaseType="android.text.ParcelableSpan" gap="33"></from><to sourceSinkType="Parameter" ParameterIndex="0" BaseType="android.text.ParcelableSpan" gap="43" taintSubFields="true"></to></flow><flow isAlias="true"><from sourceSinkType="Field" BaseType="android.content.ClipData" AccessPath="[&lt;android.content.ClipData: java.util.ArrayList mItems&gt;, &lt;java.util.ArrayList: int size&gt;]" AccessPathTypes="[java.util.ArrayList, int]"></from><to sourceSinkType="Parameter" ParameterIndex="0" BaseType="int" gap="15" taintSubFields="true"></to></flow><flow isAlias="true"><from sourceSinkType="Return" BaseType="java.lang.String" gap="29"></from><to sourceSinkType="Parameter" ParameterIndex="0" BaseType="java.lang.String" gap="22" taintSubFields="true"></to></flow><flow isAlias="true"><from sourceSinkType="Field" BaseType="android.os.Parcel" gap="25"></from><to sourceSinkType="GapBaseObject" BaseType="android.os.Parcel" gap="32"></to></flow><flow isAlias="true"><from sourceSinkType="Field" BaseType="android.net.Uri" gap="28"></from><to sourceSinkType="Field" BaseType="android.content.ClipData" AccessPath="[&lt;android.content.ClipData: java.util.ArrayList mItems&gt;, &lt;java.util.ArrayList: java.lang.Object[] array&gt;, &lt;android.content.ClipData$Item: android.net.Uri mUri&gt;]" AccessPathTypes="[java.util.ArrayList, java.lang.Object[], android.net.Uri]" taintSubFields="true"></to></flow><flow isAlias="true"><from sourceSinkType="Parameter" ParameterIndex="0" BaseType="android.os.Parcel" gap="28"></from><to sourceSinkType="Parameter" ParameterIndex="0" BaseType="android.os.Parcel" taintSubFields="true"></to></flow><flow isAlias="true"><from sourceSinkType="Field" BaseType="android.text.Spanned" gap="43"></from><to sourceSinkType="GapBaseObject" BaseType="android.text.Spanned" gap="41"></to></flow><flow isAlias="true"><from sourceSinkType="Field" BaseType="android.text.ParcelableSpan" gap="33"></from><to sourceSinkType="GapBaseObject" BaseType="android.text.ParcelableSpan" gap="40"></to></flow><flow isAlias="true"><from sourceSinkType="Field" BaseType="android.text.ParcelableSpan" gap="40"></from><to sourceSinkType="GapBaseObject" BaseType="android.text.ParcelableSpan" gap="33"></to></flow><flow isAlias="true"><from sourceSinkType="Parameter" ParameterIndex="0" BaseType="android.os.Parcel" gap="28"></from><to sourceSinkType="GapBaseObject" BaseType="android.os.Parcel" gap="17"></to></flow><flow isAlias="true"><from sourceSinkType="Field" BaseType="android.text.style.CharacterStyle" gap="39"></from><to sourceSinkType="Parameter" ParameterIndex="0" BaseType="android.text.style.CharacterStyle" gap="43" taintSubFields="true"></to></flow><flow isAlias="true"><from sourceSinkType="Parameter" ParameterIndex="1" BaseType="int"></from><to sourceSinkType="Parameter" ParameterIndex="1" BaseType="int" gap="12" taintSubFields="true"></to></flow><flow isAlias="true"><from sourceSinkType="Field" BaseType="android.text.Spanned" gap="41"></from><to sourceSinkType="Field" BaseType="android.content.ClipData" AccessPath="[&lt;android.content.ClipData: java.util.ArrayList mItems&gt;, &lt;java.util.ArrayList: java.lang.Object[] array&gt;, &lt;android.content.ClipData$Item: java.lang.CharSequence mText&gt;]" AccessPathTypes="[java.util.ArrayList, java.lang.Object[], android.text.Spanned]" taintSubFields="true"></to></flow><flow isAlias="true"><from sourceSinkType="Return" BaseType="java.lang.Object[]" gap="36"></from><to sourceSinkType="GapBaseObject" BaseType="android.text.ParcelableSpan" gap="40"></to></flow><flow isAlias="true"><from sourceSinkType="Field" BaseType="android.os.Parcel" gap="25"></from><to sourceSinkType="GapBaseObject" BaseType="android.os.Parcel" gap="21"></to></flow><flow isAlias="true"><from sourceSinkType="Field" BaseType="android.text.Spanned" gap="36"></from><to sourceSinkType="GapBaseObject" BaseType="java.lang.CharSequence" gap="31"></to></flow><flow isAlias="true"><from sourceSinkType="Field" BaseType="android.text.style.CharacterStyle" gap="39"></from><to sourceSinkType="Parameter" ParameterIndex="0" BaseType="android.text.style.CharacterStyle" gap="42" taintSubFields="true"></to></flow><flow isAlias="true"><from sourceSinkType="Field" BaseType="android.text.Spanned" gap="43"></from><to sourceSinkType="Field" BaseType="android.content.ClipData" AccessPath="[&lt;android.content.ClipData: java.util.ArrayList mItems&gt;, &lt;java.util.ArrayList: java.lang.Object[] array&gt;, &lt;android.content.ClipData$Item: java.lang.CharSequence mText&gt;]" AccessPathTypes="[java.util.ArrayList, java.lang.Object[], android.text.Spanned]" taintSubFields="true"></to></flow><flow isAlias="true"><from sourceSinkType="Field" BaseType="java.lang.CharSequence" gap="35"></from><to sourceSinkType="GapBaseObject" BaseType="android.text.Spanned" gap="36"></to></flow><flow isAlias="true"><from sourceSinkType="Parameter" ParameterIndex="0" BaseType="android.os.Parcel" gap="12"></from><to sourceSinkType="GapBaseObject" BaseType="android.os.Parcel" gap="16"></to></flow><flow isAlias="true"><from sourceSinkType="Field" BaseType="java.lang.CharSequence" gap="29"></from><to sourceSinkType="Field" BaseType="android.content.ClipData" AccessPath="[&lt;android.content.ClipData: java.util.ArrayList mItems&gt;, &lt;java.util.ArrayList: java.lang.Object[] array&gt;, &lt;android.content.ClipData$Item: java.lang.CharSequence mText&gt;]" AccessPathTypes="[java.util.ArrayList, java.lang.Object[], java.lang.CharSequence]" taintSubFields="true"></to></flow><flow isAlias="true"><from sourceSinkType="Parameter" ParameterIndex="0" BaseType="java.lang.Object" gap="41"></from><to sourceSinkType="Parameter" ParameterIndex="0" BaseType="java.lang.Object" gap="42" taintSubFields="true"></to></flow><flow isAlias="true"><from sourceSinkType="Field" BaseType="android.text.Spanned" gap="41"></from><to sourceSinkType="GapBaseObject" BaseType="android.text.Spanned" gap="42"></to></flow><flow isAlias="true"><from sourceSinkType="Field" BaseType="android.text.Spanned" gap="42"></from><to sourceSinkType="GapBaseObject" BaseType="android.text.Spanned" gap="41"></to></flow><flow isAlias="true"><from sourceSinkType="Field" BaseType="android.content.ClipDescription" gap="12"></from><to sourceSinkType="Field" BaseType="android.content.ClipData" AccessPath="[&lt;android.content.ClipData: android.content.ClipDescription mClipDescription&gt;]" AccessPathTypes="[android.content.ClipDescription]" taintSubFields="true"></to></flow><flow isAlias="true"><from sourceSinkType="Field" BaseType="android.text.ParcelableSpan" gap="33"></from><to sourceSinkType="Parameter" ParameterIndex="0" BaseType="android.text.ParcelableSpan" gap="42" taintSubFields="true"></to></flow><flow isAlias="true"><from sourceSinkType="Field" BaseType="android.text.Spanned" gap="42"></from><to sourceSinkType="GapBaseObject" BaseType="java.lang.CharSequence" gap="29"></to></flow><flow isAlias="true"><from sourceSinkType="Field" BaseType="android.content.ClipData" AccessPath="[&lt;android.content.ClipData: java.util.ArrayList mItems&gt;, &lt;java.util.ArrayList: java.lang.Object[] array&gt;, &lt;android.content.ClipData$Item: java.lang.CharSequence mText&gt;]" AccessPathTypes="[java.util.ArrayList, java.lang.Object[], java.lang.CharSequence]"></from><to sourceSinkType="GapBaseObject" BaseType="java.lang.CharSequence" gap="29"></to></flow><flow isAlias="true"><from sourceSinkType="Return" BaseType="java.lang.Object[]" gap="36"></from><to sourceSinkType="Parameter" ParameterIndex="0" BaseType="java.lang.Object" gap="41" taintSubFields="true"></to></flow><flow isAlias="true"><from sourceSinkType="Field" BaseType="android.text.ParcelableSpan" gap="40"></from><to sourceSinkType="Parameter" ParameterIndex="0" BaseType="android.text.ParcelableSpan" gap="41" taintSubFields="true"></to></flow><flow isAlias="true"><from sourceSinkType="Field" BaseType="android.os.Parcel" gap="17"></from><to sourceSinkType="GapBaseObject" BaseType="android.os.Parcel" gap="19"></to></flow><flow isAlias="true"><from sourceSinkType="Field" BaseType="java.lang.CharSequence" gap="35"></from><to sourceSinkType="GapBaseObject" BaseType="java.lang.CharSequence" gap="31"></to></flow><flow isAlias="true"><from sourceSinkType="Parameter" ParameterIndex="0" BaseType="android.os.Parcel" gap="14"></from><to sourceSinkType="GapBaseObject" BaseType="android.os.Parcel" gap="15"></to></flow><flow isAlias="true"><from sourceSinkType="Parameter" ParameterIndex="0" BaseType="android.os.Parcel" gap="23"></from><to sourceSinkType="GapBaseObject" BaseType="android.os.Parcel" gap="24"></to></flow><flow isAlias="true"><from sourceSinkType="Parameter" ParameterIndex="0" BaseType="android.os.Parcel" gap="33"></from><to sourceSinkType="GapBaseObject" BaseType="android.os.Parcel" gap="34"></to></flow><flow isAlias="true"><from sourceSinkType="Field" BaseType="android.os.Parcel" gap="15"></from><to sourceSinkType="GapBaseObject" BaseType="android.os.Parcel" gap="17"></to></flow></flows></method><method id="java.lang.String toString()"><flows><flow isAlias="true"><from sourceSinkType="Parameter" ParameterIndex="0" BaseType="java.lang.StringBuilder" AccessPath="[&lt;java.lang.AbstractStringBuilder: int count&gt;]" AccessPathTypes="[int]" gap="11"></from><to sourceSinkType="Return" BaseType="java.lang.String" AccessPath="[&lt;java.lang.String: char[] value&gt;]" AccessPathTypes="[char[]]" taintSubFields="true"></to></flow><flow isAlias="true"><from sourceSinkType="Field" BaseType="android.content.ClipData" AccessPath="[&lt;android.content.ClipData: android.content.ClipDescription mClipDescription&gt;]" AccessPathTypes="[android.content.ClipDescription]"></from><to sourceSinkType="GapBaseObject" BaseType="android.content.ClipDescription" gap="8"></to></flow><flow isAlias="true"><from sourceSinkType="Parameter" ParameterIndex="0" BaseType="java.lang.StringBuilder" AccessPath="[&lt;java.lang.AbstractStringBuilder: int count&gt;]" AccessPathTypes="[int]" gap="11"></from><to sourceSinkType="Return" BaseType="java.lang.String" AccessPath="[&lt;java.lang.String: int count&gt;]" AccessPathTypes="[int]" taintSubFields="true"></to></flow><flow isAlias="true"><from sourceSinkType="Field" BaseType="android.content.ClipData$Item" gap="11"></from><to sourceSinkType="Field" BaseType="android.content.ClipData" AccessPath="[&lt;android.content.ClipData: java.util.ArrayList mItems&gt;, &lt;java.util.ArrayList: java.lang.Object[] array&gt;]" AccessPathTypes="[java.util.ArrayList, java.lang.Object[]]" taintSubFields="true"></to></flow><flow isAlias="true"><from sourceSinkType="Parameter" ParameterIndex="0" BaseType="java.lang.StringBuilder" AccessPath="[&lt;java.lang.AbstractStringBuilder: char[] value&gt;]" AccessPathTypes="[char[]]" gap="11"></from><to sourceSinkType="Return" BaseType="java.lang.String" AccessPath="[&lt;java.lang.String: char[] value&gt;]" AccessPathTypes="[char[]]" taintSubFields="true"></to></flow><flow isAlias="true"><from sourceSinkType="Parameter" ParameterIndex="0" BaseType="java.lang.StringBuilder" AccessPath="[&lt;java.lang.AbstractStringBuilder: int count&gt;]" AccessPathTypes="[int]" gap="8"></from><to sourceSinkType="Field" BaseType="java.lang.StringBuilder" AccessPath="[&lt;java.lang.AbstractStringBuilder: int count&gt;]" AccessPathTypes="[int]" gap="8" taintSubFields="true"></to></flow><flow isAlias="true"><from sourceSinkType="Field" BaseType="android.content.ClipData" AccessPath="[&lt;android.content.ClipData: android.graphics.Bitmap mIcon&gt;]" AccessPathTypes="[android.graphics.Bitmap]"></from><to sourceSinkType="GapBaseObject" BaseType="android.graphics.Bitmap" gap="10"></to></flow><flow isAlias="true"><from sourceSinkType="Field" BaseType="android.graphics.Bitmap" gap="9"></from><to sourceSinkType="GapBaseObject" BaseType="android.graphics.Bitmap" gap="10"></to></flow><flow isAlias="true"><from sourceSinkType="Parameter" ParameterIndex="0" BaseType="java.lang.StringBuilder" AccessPath="[&lt;java.lang.AbstractStringBuilder: char[] value&gt;]" AccessPathTypes="[char[]]" gap="8"></from><to sourceSinkType="Return" BaseType="java.lang.String" AccessPath="[&lt;java.lang.String: char[] value&gt;]" AccessPathTypes="[char[]]" taintSubFields="true"></to></flow><flow isAlias="true"><from sourceSinkType="Field" BaseType="android.content.ClipData" AccessPath="[&lt;android.content.ClipData: java.util.ArrayList mItems&gt;, &lt;java.util.ArrayList: java.lang.Object[] array&gt;]" AccessPathTypes="[java.util.ArrayList, java.lang.Object[]]"></from><to sourceSinkType="GapBaseObject" BaseType="android.content.ClipData$Item" gap="11"></to></flow><flow isAlias="true"><from sourceSinkType="Field" BaseType="android.graphics.Bitmap" gap="9"></from><to sourceSinkType="Field" BaseType="android.content.ClipData" AccessPath="[&lt;android.content.ClipData: android.graphics.Bitmap mIcon&gt;]" AccessPathTypes="[android.graphics.Bitmap]" taintSubFields="true"></to></flow><flow isAlias="true"><from sourceSinkType="Parameter" ParameterIndex="0" BaseType="java.lang.StringBuilder" AccessPath="[&lt;java.lang.AbstractStringBuilder: int count&gt;]" AccessPathTypes="[int]" gap="8"></from><to sourceSinkType="Field" BaseType="java.lang.StringBuilder" AccessPath="[&lt;java.lang.AbstractStringBuilder: int count&gt;]" AccessPathTypes="[int]" gap="11" taintSubFields="true"></to></flow><flow isAlias="true"><from sourceSinkType="Parameter" ParameterIndex="0" BaseType="java.lang.StringBuilder" AccessPath="[&lt;java.lang.AbstractStringBuilder: int count&gt;]" AccessPathTypes="[int]" gap="11"></from><to sourceSinkType="Field" BaseType="java.lang.StringBuilder" AccessPath="[&lt;java.lang.AbstractStringBuilder: int count&gt;]" AccessPathTypes="[int]" gap="8" taintSubFields="true"></to></flow><flow isAlias="true"><from sourceSinkType="Field" BaseType="android.graphics.Bitmap" gap="10"></from><to sourceSinkType="Field" BaseType="android.content.ClipData" AccessPath="[&lt;android.content.ClipData: android.graphics.Bitmap mIcon&gt;]" AccessPathTypes="[android.graphics.Bitmap]" taintSubFields="true"></to></flow><flow isAlias="true"><from sourceSinkType="Parameter" ParameterIndex="0" BaseType="java.lang.StringBuilder" AccessPath="[&lt;java.lang.AbstractStringBuilder: int count&gt;]" AccessPathTypes="[int]" gap="11"></from><to sourceSinkType="Parameter" ParameterIndex="0" BaseType="java.lang.StringBuilder" AccessPath="[&lt;java.lang.AbstractStringBuilder: char[] value&gt;]" AccessPathTypes="[char[]]" gap="11" taintSubFields="true"></to></flow><flow isAlias="true"><from sourceSinkType="Field" BaseType="android.content.ClipDescription" gap="8"></from><to sourceSinkType="Field" BaseType="android.content.ClipData" AccessPath="[&lt;android.content.ClipData: android.content.ClipDescription mClipDescription&gt;]" AccessPathTypes="[android.content.ClipDescription]" taintSubFields="true"></to></flow><flow isAlias="true"><from sourceSinkType="Parameter" ParameterIndex="0" BaseType="java.lang.StringBuilder" AccessPath="[&lt;java.lang.AbstractStringBuilder: int count&gt;]" AccessPathTypes="[int]" gap="11"></from><to sourceSinkType="Field" BaseType="java.lang.StringBuilder" AccessPath="[&lt;java.lang.AbstractStringBuilder: int count&gt;]" AccessPathTypes="[int]" gap="11" taintSubFields="true"></to></flow><flow isAlias="true"><from sourceSinkType="Parameter" ParameterIndex="0" BaseType="java.lang.StringBuilder" AccessPath="[&lt;java.lang.AbstractStringBuilder: int count&gt;]" AccessPathTypes="[int]" gap="8"></from><to sourceSinkType="Return" BaseType="java.lang.String" AccessPath="[&lt;java.lang.String: char[] value&gt;]" AccessPathTypes="[char[]]" taintSubFields="true"></to></flow><flow isAlias="true"><from sourceSinkType="Field" BaseType="android.content.ClipData" AccessPath="[&lt;android.content.ClipData: android.graphics.Bitmap mIcon&gt;]" AccessPathTypes="[android.graphics.Bitmap]"></from><to sourceSinkType="GapBaseObject" BaseType="android.graphics.Bitmap" gap="9"></to></flow><flow isAlias="true"><from sourceSinkType="Parameter" ParameterIndex="0" BaseType="java.lang.StringBuilder" AccessPath="[&lt;java.lang.AbstractStringBuilder: int count&gt;]" AccessPathTypes="[int]" gap="8"></from><to sourceSinkType="Return" BaseType="java.lang.String" AccessPath="[&lt;java.lang.String: int count&gt;]" AccessPathTypes="[int]" taintSubFields="true"></to></flow><flow isAlias="true"><from sourceSinkType="Parameter" ParameterIndex="0" BaseType="java.lang.StringBuilder" gap="8"></from><to sourceSinkType="Parameter" ParameterIndex="0" BaseType="java.lang.StringBuilder" gap="11" taintSubFields="true"></to></flow></flows></method><method id="void &lt;init&gt;(android.content.ClipData)"><flows><flow isAlias="true"><from sourceSinkType="Parameter" ParameterIndex="0" BaseType="android.content.ClipData" AccessPath="[&lt;android.content.ClipData: java.util.ArrayList mItems&gt;]" AccessPathTypes="[java.util.ArrayList]"></from><to sourceSinkType="GapBaseObject" BaseType="java.util.ArrayList" gap="0"></to></flow><flow isAlias="true"><from sourceSinkType="Parameter" ParameterIndex="0" BaseType="android.content.ClipData" AccessPath="[&lt;android.content.ClipData: android.graphics.Bitmap mIcon&gt;]" AccessPathTypes="[android.graphics.Bitmap]"></from><to sourceSinkType="Field" BaseType="android.content.ClipData" AccessPath="[&lt;android.content.ClipData: android.graphics.Bitmap mIcon&gt;]" AccessPathTypes="[android.graphics.Bitmap]" taintSubFields="true"></to></flow><flow isAlias="true"><from sourceSinkType="Field" BaseType="java.util.ArrayList" gap="0"></from><to sourceSinkType="Parameter" ParameterIndex="0" BaseType="android.content.ClipData" AccessPath="[&lt;android.content.ClipData: java.util.ArrayList mItems&gt;]" AccessPathTypes="[java.util.ArrayList]" taintSubFields="true"></to></flow><flow isAlias="true"><from sourceSinkType="Parameter" ParameterIndex="0" BaseType="android.content.ClipData" AccessPath="[&lt;android.content.ClipData: android.content.ClipDescription mClipDescription&gt;]" AccessPathTypes="[android.content.ClipDescription]"></from><to sourceSinkType="Field" BaseType="android.content.ClipData" AccessPath="[&lt;android.content.ClipData: android.content.ClipDescription mClipDescription&gt;]" AccessPathTypes="[android.content.ClipDescription]" taintSubFields="true"></to></flow><flow isAlias="true"><from sourceSinkType="Return" BaseType="java.lang.Object[]" gap="0"></from><to sourceSinkType="Field" BaseType="android.content.ClipData" AccessPath="[&lt;android.content.ClipData: java.util.ArrayList mItems&gt;, &lt;java.util.ArrayList: int size&gt;]" AccessPathTypes="[java.util.ArrayList, int]" taintSubFields="true"></to></flow><flow isAlias="true"><from sourceSinkType="Return" BaseType="java.lang.Object[]" gap="0"></from><to sourceSinkType="Field" BaseType="android.content.ClipData" AccessPath="[&lt;android.content.ClipData: java.util.ArrayList mItems&gt;, &lt;java.util.ArrayList: java.lang.Object[] array&gt;]" AccessPathTypes="[java.util.ArrayList, java.lang.Object[]]" taintSubFields="true"></to></flow></flows></method><method id="android.content.ClipData newPlainText(java.lang.CharSequence,java.lang.CharSequence)"><flows><flow isAlias="true"><from sourceSinkType="Parameter" ParameterIndex="0" BaseType="java.lang.CharSequence"></from><to sourceSinkType="Return" BaseType="android.content.ClipData" AccessPath="[&lt;android.content.ClipData: android.content.ClipDescription mClipDescription&gt;, &lt;android.content.ClipDescription: java.lang.CharSequence mLabel&gt;]" AccessPathTypes="[android.content.ClipDescription, java.lang.CharSequence]" taintSubFields="true"></to></flow><flow isAlias="true"><from sourceSinkType="Parameter" ParameterIndex="1" BaseType="java.lang.CharSequence"></from><to sourceSinkType="Return" BaseType="android.content.ClipData" AccessPath="[&lt;android.content.ClipData: java.util.ArrayList mItems&gt;, &lt;java.util.ArrayList: java.lang.Object[] array&gt;, &lt;android.content.ClipData$Item: java.lang.CharSequence mText&gt;]" AccessPathTypes="[java.util.ArrayList, android.content.ClipData$Item[], java.lang.CharSequence]" taintSubFields="true"></to></flow></flows></method><method id="android.content.ClipData newIntent(java.lang.CharSequence,android.content.Intent)"><flows><flow isAlias="true"><from sourceSinkType="Parameter" ParameterIndex="0" BaseType="java.lang.CharSequence"></from><to sourceSinkType="Return" BaseType="android.content.ClipData" AccessPath="[&lt;android.content.ClipData: android.content.ClipDescription mClipDescription&gt;, &lt;android.content.ClipDescription: java.lang.CharSequence mLabel&gt;]" AccessPathTypes="[android.content.ClipDescription, java.lang.CharSequence]" taintSubFields="true"></to></flow><flow isAlias="true"><from sourceSinkType="Parameter" ParameterIndex="1" BaseType="android.content.Intent"></from><to sourceSinkType="Return" BaseType="android.content.ClipData" AccessPath="[&lt;android.content.ClipData: java.util.ArrayList mItems&gt;, &lt;java.util.ArrayList: java.lang.Object[] array&gt;, &lt;android.content.ClipData$Item: android.content.Intent mIntent&gt;]" AccessPathTypes="[java.util.ArrayList, android.content.ClipData$Item[], android.content.Intent]" taintSubFields="true"></to></flow></flows></method><method id="android.content.ClipDescription getDescription()"><flows><flow isAlias="true"><from sourceSinkType="Field" BaseType="android.content.ClipData" AccessPath="[&lt;android.content.ClipData: android.content.ClipDescription mClipDescription&gt;]" AccessPathTypes="[android.content.ClipDescription]"></from><to sourceSinkType="Return" BaseType="android.content.ClipDescription" taintSubFields="true"></to></flow></flows></method><method id="void addItem(android.content.ClipData$Item)"><flows><flow isAlias="true"><from sourceSinkType="Field" BaseType="android.content.ClipData" AccessPath="[&lt;android.content.ClipData: java.util.ArrayList mItems&gt;, &lt;java.util.ArrayList: int size&gt;]" AccessPathTypes="[java.util.ArrayList, int]"></from><to sourceSinkType="Field" BaseType="android.content.ClipData" AccessPath="[&lt;android.content.ClipData: java.util.ArrayList mItems&gt;, &lt;java.util.ArrayList: java.lang.Object[] array&gt;]" AccessPathTypes="[java.util.ArrayList, java.lang.Object[]]" taintSubFields="true"></to></flow><flow isAlias="true"><from sourceSinkType="Parameter" ParameterIndex="0" BaseType="android.content.ClipData$Item"></from><to sourceSinkType="Field" BaseType="android.content.ClipData" AccessPath="[&lt;android.content.ClipData: java.util.ArrayList mItems&gt;, &lt;java.util.ArrayList: java.lang.Object[] array&gt;]" AccessPathTypes="[java.util.ArrayList, android.content.ClipData$Item[]]" taintSubFields="true"></to></flow></flows></method></methods><gaps><gap num="0" id="&lt;java.util.Collection: java.lang.Object[] toArray()&gt;"></gap><gap num="1" id="&lt;android.net.Uri: java.lang.String getScheme()&gt;"></gap><gap num="2" id="&lt;android.content.ContentResolver: java.lang.String getType(android.net.Uri)&gt;"></gap><gap num="3" id="&lt;android.content.ContentResolver: java.lang.String[] getStreamTypes(android.net.Uri,java.lang.String)&gt;"></gap><gap num="4" id="&lt;android.content.ClipDescription: boolean toShortString(java.lang.StringBuilder)&gt;"></gap><gap num="5" id="&lt;android.graphics.Bitmap: int getWidth()&gt;"></gap><gap num="6" id="&lt;android.graphics.Bitmap: int getHeight()&gt;"></gap><gap num="7" id="&lt;android.content.ClipData$Item: void toShortString(java.lang.StringBuilder)&gt;"></gap><gap num="8" id="&lt;android.content.ClipDescription: boolean toShortString(java.lang.StringBuilder)&gt;"></gap><gap num="9" id="&lt;android.graphics.Bitmap: int getWidth()&gt;"></gap><gap num="10" id="&lt;android.graphics.Bitmap: int getHeight()&gt;"></gap><gap num="11" id="&lt;android.content.ClipData$Item: void toShortString(java.lang.StringBuilder)&gt;"></gap><gap num="12" id="&lt;android.content.ClipDescription: void writeToParcel(android.os.Parcel,int)&gt;"></gap><gap num="13" id="&lt;android.os.Parcel: void writeInt(int)&gt;"></gap><gap num="14" id="&lt;android.graphics.Bitmap: void writeToParcel(android.os.Parcel,int)&gt;"></gap><gap num="15" id="&lt;android.os.Parcel: void writeInt(int)&gt;"></gap><gap num="16" id="&lt;android.os.Parcel: void writeInt(int)&gt;"></gap><gap num="17" id="&lt;android.os.Parcel: void writeString(java.lang.String)&gt;"></gap><gap num="18" id="&lt;android.os.Parcel: void writeInt(int)&gt;"></gap><gap num="19" id="&lt;android.os.Parcel: void writeInt(int)&gt;"></gap><gap num="20" id="&lt;android.os.Parcel: void writeInt(int)&gt;"></gap><gap num="21" id="&lt;android.os.Parcel: void writeInt(int)&gt;"></gap><gap num="22" id="&lt;android.os.Parcel: void writeString(java.lang.String)&gt;"></gap><gap num="23" id="&lt;android.content.Intent: void writeToParcel(android.os.Parcel,int)&gt;"></gap><gap num="24" id="&lt;android.os.Parcel: void writeInt(int)&gt;"></gap><gap num="25" id="&lt;android.os.Parcel: void writeInt(int)&gt;"></gap><gap num="28" id="&lt;android.os.Parcelable: void writeToParcel(android.os.Parcel,int)&gt;"></gap><gap num="29" id="&lt;java.lang.Object: java.lang.String toString()&gt;"></gap><gap num="31" id="&lt;java.lang.Object: java.lang.String toString()&gt;"></gap><gap num="32" id="&lt;android.os.Parcel: void writeInt(int)&gt;"></gap><gap num="33" id="&lt;android.os.Parcelable: void writeToParcel(android.os.Parcel,int)&gt;"></gap><gap num="34" id="&lt;android.os.Parcel: void writeInt(int)&gt;"></gap><gap num="35" id="&lt;java.lang.CharSequence: int length()&gt;"></gap><gap num="36" id="&lt;android.text.Spanned: java.lang.Object[] getSpans(int,int,java.lang.Class)&gt;"></gap><gap num="37" id="&lt;android.os.Parcel: void writeInt(int)&gt;"></gap><gap num="39" id="&lt;android.text.style.CharacterStyle: android.text.style.CharacterStyle getUnderlying()&gt;"></gap><gap num="40" id="&lt;android.text.ParcelableSpan: int getSpanTypeId()&gt;"></gap><gap num="41" id="&lt;android.text.Spanned: int getSpanStart(java.lang.Object)&gt;"></gap><gap num="42" id="&lt;android.text.Spanned: int getSpanEnd(java.lang.Object)&gt;"></gap><gap num="43" id="&lt;android.text.Spanned: int getSpanFlags(java.lang.Object)&gt;"></gap></gaps></summary>